nltkbleu/__init__.py
nltkbleu/bleud.py
nltkbleu-0.1.2.dist-info/LICENSE.txt
nltkbleu-0.1.2.dist-info/METADATA
nltkbleu-0.1.2.dist-info/WHEEL
nltkbleu-0.1.2.dist-info/top_level.txt
nltkbleu-0.1.2.dist-info/RECORD
