Metadata-Version: 2.1
Name: nltkbleu
Version: 0.1.2
Summary: A nltk scoring and text utility module with TensorFlow and NLP tools.
Home-page: https://github.com/yourusername/nltkbleu
Author: pixelpilot24
Author-email: pixelpilot24@gmail.com
License: MIT
Requires-Python: >=3.7
License-File: LICENSE.txt
Requires-Dist: numpy
Requires-Dist: pandas
